{"data":{"site":{"siteMetadata":{"title":"Daily Log","author":"Jiyeon Seo"}},"markdownRemark":{"id":"5908b286-d9a4-5b06-b106-3b48dfcb7a3d","excerpt":"This is the first blog. \nLet me move the previous blog to here. ","html":"<p>This is the first blog.\nLet me move the previous blog to here. </p>","frontmatter":{"title":"The First Blog!","date":"January 11, 2018"}}},"pageContext":{"slug":"/thisisnew/","previous":{"fields":{"slug":"/hello-world/"},"frontmatter":{"title":"Hello World"}},"next":{"fields":{"slug":"/my-second-post/"},"frontmatter":{"title":"My Second Post!"}}}}